heimdall/__init__.py
heimdall/core.py
heimdall/prompts.py
pst_heimdall-1.0.dist-info/licenses/LICENSE
pst_heimdall-1.0.dist-info/METADATA
pst_heimdall-1.0.dist-info/WHEEL
pst_heimdall-1.0.dist-info/top_level.txt
pst_heimdall-1.0.dist-info/RECORD
