Metadata-Version: 2.4
Name: pst_heimdall
Version: 1.0
Summary: LLM validation wrapper
Author-email: prophet_system_team <vivekvjnk@gmail.com>
License: 
Requires-Python: >=3.10
License-File: LICENSE
Dynamic: license-file
